MANIFEST.in
README.rst
setup.py
restfulgrok/__init__.py
restfulgrok/contenttype.py
restfulgrok/example.py
restfulgrok/example_tests.py
restfulgrok/fancyhtmlview.py
restfulgrok/mock.py
restfulgrok/tests.py
restfulgrok/view.py
restfulgrok.egg-info/PKG-INFO
restfulgrok.egg-info/SOURCES.txt
restfulgrok.egg-info/dependency_links.txt
restfulgrok.egg-info/requires.txt
restfulgrok.egg-info/top_level.txt
restfulgrok.egg-info/zip-safe
restfulgrok/templates/errorview.jinja.html
restfulgrok/templates/fancyhtmlview.jinja.html