Metadata-Version: 1.0
Name: restfulgrok
Version: 1.0.2
Summary: RESTful interface for grok (and five.grok).
Home-page: https://github.com/espenak/restfulgrok
Author: Espen Angell Kristiansen
Author-email: post@espenak.net
License: BSD
Platform: UNKNOWN
Classifier: Development Status :: 5 - Production/Stable
Classifier: Environment :: Web Environment
Classifier: Framework :: Plone
Classifier: Intended Audience :: Developers
Classifier: License :: OSI Approved
Classifier: Operating System :: OS Independent
Classifier: Programming Language :: Python
